{
  "annotations": {
    "list": [
      {
        "builtIn": 1,
        "datasource": "-- Grafana --",
        "enable": true,
        "hide": true,
        "iconColor": "rgba(0, 211, 255, 1)",
        "name": "Annotations & Alerts",
        "target": {
          "limit": 100,
          "matchAny": false,
          "tags": [],
          "type": "dashboard"
        },
        "type": "dashboard"
      }
    ]
  },
  "editable": true,
  "gnetId": null,
  "graphTooltip": 0,
  "id": 3,
  "links": [],
  "panels": [
    {
      "datasource": "mysql",
      "description": "",
      "fieldConfig": {
        "defaults": {
          "color": {
            "mode": "palette-classic"
          },
          "custom": {
            "hideFrom": {
              "legend": false,
              "tooltip": false,
              "viz": false
            }
          },
          "mappings": []
        },
        "overrides": []
      },
      "gridPos": {
        "h": 8,
        "w": 12,
        "x": 0,
        "y": 0
      },
      "id": 4,
      "interval": "1h",
      "maxDataPoints": 800,
      "options": {
        "displayLabels": [
          "percent"
        ],
        "legend": {
          "displayMode": "table",
          "placement": "right",
          "values": [
            "value"
          ]
        },
        "pieType": "pie",
        "reduceOptions": {
          "calcs": [
            "distinctCount"
          ],
          "fields": "",
          "values": false
        },
        "tooltip": {
          "mode": "single"
        }
      },
      "targets": [
        {
          "format": "time_series",
          "group": [
            {
              "params": [
                "buildresult"
              ],
              "type": "column"
            }
          ],
          "metricColumn": "none",
          "queryType": "randomWalk",
          "rawQuery": true,
          "rawSql": "SELECT\r\nUNIX_TIMESTAMP(buildstart) as \"time\",\r\nbuildresult,\r\n  count(task_id) as \"cnt\"\r\nFROM Task\r\nwhere $__timeFilter(buildstart)\r\ngroup by 1,2\r\nORDER BY time",
          "refId": "A",
          "select": [
            [
              {
                "params": [
                  "buildresult"
                ],
                "type": "column"
              },
              {
                "params": [
                  "count"
                ],
                "type": "aggregate"
              },
              {
                "params": [
                  "result"
                ],
                "type": "alias"
              }
            ]
          ],
          "table": "Task",
          "timeColumn": "buildstart",
          "timeColumnType": "timestamp",
          "where": [
            {
              "name": "$__timeFilter",
              "params": [],
              "type": "macro"
            }
          ]
        }
      ],
      "timeFrom": null,
      "timeShift": null,
      "title": "Task Overall Build Results",
      "transformations": [
        {
          "id": "groupBy",
          "options": {}
        }
      ],
      "type": "piechart"
    },
    {
      "datasource": "mysql",
      "fieldConfig": {
        "defaults": {
          "color": {
            "mode": "palette-classic"
          },
          "custom": {
            "axisLabel": "",
            "axisPlacement": "auto",
            "barAlignment": 0,
            "drawStyle": "line",
            "fillOpacity": 0,
            "gradientMode": "none",
            "hideFrom": {
              "legend": false,
              "tooltip": false,
              "viz": false
            },
            "lineInterpolation": "linear",
            "lineWidth": 1,
            "pointSize": 5,
            "scaleDistribution": {
              "type": "linear"
            },
            "showPoints": "auto",
            "spanNulls": false,
            "stacking": {
              "group": "A",
              "mode": "none"
            },
            "thresholdsStyle": {
              "mode": "off"
            }
          },
          "mappings": [],
          "thresholds": {
            "mode": "absolute",
            "steps": [
              {
                "color": "green",
                "value": null
              },
              {
                "color": "red",
                "value": 80
              }
            ]
          }
        },
        "overrides": []
      },
      "gridPos": {
        "h": 9,
        "w": 12,
        "x": 0,
        "y": 8
      },
      "id": 2,
      "interval": "1m",
      "options": {
        "legend": {
          "calcs": [],
          "displayMode": "list",
          "placement": "bottom"
        },
        "tooltip": {
          "mode": "single"
        }
      },
      "targets": [
        {
          "format": "time_series",
          "group": [
            {
              "params": [
                "$__interval",
                "none"
              ],
              "type": "time"
            }
          ],
          "metricColumn": "none",
          "rawQuery": false,
          "rawSql": "SELECT\n  $__timeGroupAlias(buildstart,$__interval),\n  count(task_id) AS \"building_taks\"\nFROM Task\nWHERE\n  $__timeFilter(buildstart)\nGROUP BY 1\nORDER BY $__timeGroup(buildstart,$__interval)",
          "refId": "A",
          "select": [
            [
              {
                "params": [
                  "task_id"
                ],
                "type": "column"
              },
              {
                "params": [
                  "count"
                ],
                "type": "aggregate"
              },
              {
                "params": [
                  "building_taks"
                ],
                "type": "alias"
              }
            ]
          ],
          "table": "Task",
          "timeColumn": "buildstart",
          "timeColumnType": "timestamp",
          "where": [
            {
              "name": "$__timeFilter",
              "params": [],
              "type": "macro"
            }
          ]
        }
      ],
      "title": "Building Times",
      "type": "timeseries"
    }
  ],
  "refresh": false,
  "schemaVersion": 30,
  "style": "dark",
  "tags": [],
  "templating": {
    "list": []
  },
  "time": {
    "from": "2021-04-19T16:12:43.292Z",
    "to": "2021-04-19T16:55:16.892Z"
  },
  "timepicker": {},
  "timezone": "",
  "title": "Sample_SDK_Dashboard",
  "uid": "iDVMAknnz",
  "version": 5
}